libname/__init__.py
libname/app.py
Odyssi-0.0.1.dist-info/METADATA
Odyssi-0.0.1.dist-info/WHEEL
Odyssi-0.0.1.dist-info/top_level.txt
Odyssi-0.0.1.dist-info/RECORD
