Metadata-Version: 2.1
Name: Odyssi
Version: 0.0.1
Summary: Odyssi
Home-page: UNKNOWN
Author: Polly
Author-email: <dikshyamn327@gmail.com>
License: UNKNOWN
Keywords: python,chatbot,oretes,programming for life
Platform: UNKNOWN
Classifier: Development Status :: 1 - Planning
Classifier: Intended Audience :: Developers
Classifier: Programming Language :: Python :: 3
Classifier: Operating System :: Unix
Classifier: Operating System :: MacOS :: MacOS X
Classifier: Operating System :: Microsoft :: Windows
